sandworm/__init__.py
sandworm/cli.py
sandworm/core.py
sandworm/helpers.py
sandworm/run.py
sandworm_build-0.3.0.dist-info/WHEEL
sandworm_build-0.3.0.dist-info/entry_points.txt
sandworm_build-0.3.0.dist-info/METADATA
sandworm_build-0.3.0.dist-info/RECORD
