Metadata-Version: 2.3
Name: sandworm-build
Version: 0.3.0
Summary: Minimalistic build tool inspired by Make
Keywords: build,build-tool,automation
Author: Daniel Walker
Author-email: Daniel Walker <nickeldan@gmail.com>
License: MIT License
Classifier: License :: OSI Approved :: MIT License
Classifier: Programming Language :: Python :: 3
Classifier: Programming Language :: Python :: 3 :: Only
Classifier: Programming Language :: Python :: 3.10
Classifier: Environment :: Console
Classifier: Topic :: Software Development :: Build Tools
Requires-Dist: click>=8.3.1
Requires-Dist: python-dotenv>=1.2.1
Requires-Python: >=3.10.0
Project-URL: Repository, https://gitlab.com/nickeldan/sandworm
